decoder/__init__.py
decoder/decode_jinja2_3_0.py
decoder/decoder.py
decoder/job-definition-schema.yaml
decoder/manifest-schema.yaml
im_data_manager_job_decoder-2.5.0.dist-info/licenses/LICENSE
im_data_manager_job_decoder-2.5.0.dist-info/METADATA
im_data_manager_job_decoder-2.5.0.dist-info/WHEEL
im_data_manager_job_decoder-2.5.0.dist-info/top_level.txt
im_data_manager_job_decoder-2.5.0.dist-info/RECORD
