Metadata-Version: 2.4
Name: im-data-manager-job-decoder
Version: 2.5.0
Summary: Job decoding logic
Home-page: https://github.com/informaticsmatters/squonk2-data-manager-job-decoder
Author: Alan Christie
Author-email: achristie@informaticsmatters.com
License: MIT
Keywords: jinja2 decoder
Platform: any
Classifier: Development Status :: 5 - Production/Stable
Classifier: Environment :: Other Environment
Classifier: Intended Audience :: Developers
Classifier: License :: OSI Approved :: MIT License
Classifier: Programming Language :: Python :: 3.10
Classifier: Programming Language :: Python :: 3.11
Classifier: Programming Language :: Python :: 3.12
Classifier: Topic :: Software Development :: Libraries :: Python Modules
Classifier: Operating System :: POSIX :: Linux
Requires-Python: >=3.10
License-File: LICENSE
Requires-Dist: jinja2==3.1.3
Requires-Dist: jsonschema<5.0,>=4.21.1
Requires-Dist: pyyaml<7.0,>=5.3.1
Dynamic: author
Dynamic: author-email
Dynamic: classifier
Dynamic: description
Dynamic: home-page
Dynamic: keywords
Dynamic: license
Dynamic: license-file
Dynamic: platform
Dynamic: requires-dist
Dynamic: requires-python
Dynamic: summary
